rich_grid/__init__.py
rich_grid-0.1.3.dist-info/METADATA
rich_grid-0.1.3.dist-info/WHEEL
rich_grid-0.1.3.dist-info/RECORD
