Metadata-Version: 2.1
Name: rich-grid
Version: 0.1.3
Summary: 
Author: uname-n
Author-email: git@defend.sh
Requires-Python: >=3.12,<4.0
Classifier: Programming Language :: Python :: 3
Classifier: Programming Language :: Python :: 3.12
Classifier: Programming Language :: Python :: 3.13
Requires-Dist: numpy (>=2.2.2,<3.0.0)
Requires-Dist: pydantic (>=2.10.5,<3.0.0)
Requires-Dist: rich (>=13.9.4,<14.0.0)
